NiukeWangMingqiBishiMianshiQiuzhiGonglveSidaXingye20202021/README.md
NiukeWangMingqiBishiMianshiQiuzhiGonglveSidaXingye20202021/__init__.py
NiukeWangMingqiBishiMianshiQiuzhiGonglveSidaXingye20202021/__main__.py
NiukeWangMingqiBishiMianshiQiuzhiGonglveSidaXingye20202021/file.epub
NiukeWangMingqiBishiMianshiQiuzhiGonglveSidaXingye20202021/index.html
NiukeWangMingqiBishiMianshiQiuzhiGonglveSidaXingye20202021/css/__init__.py
NiukeWangMingqiBishiMianshiQiuzhiGonglveSidaXingye20202021/css/annotations.css
NiukeWangMingqiBishiMianshiQiuzhiGonglveSidaXingye20202021/css/main.css
NiukeWangMingqiBishiMianshiQiuzhiGonglveSidaXingye20202021/css/normalize.css
NiukeWangMingqiBishiMianshiQiuzhiGonglveSidaXingye20202021/css/popup.css
NiukeWangMingqiBishiMianshiQiuzhiGonglveSidaXingye20202021/font/__init__.py
NiukeWangMingqiBishiMianshiQiuzhiGonglveSidaXingye20202021/font/fontello.eot
NiukeWangMingqiBishiMianshiQiuzhiGonglveSidaXingye20202021/font/fontello.svg
NiukeWangMingqiBishiMianshiQiuzhiGonglveSidaXingye20202021/font/fontello.ttf
NiukeWangMingqiBishiMianshiQiuzhiGonglveSidaXingye20202021/font/fontello.woff
NiukeWangMingqiBishiMianshiQiuzhiGonglveSidaXingye20202021/img/__init__.py
NiukeWangMingqiBishiMianshiQiuzhiGonglveSidaXingye20202021/img/annotator-glyph-sprite.png
NiukeWangMingqiBishiMianshiQiuzhiGonglveSidaXingye20202021/img/annotator-icon-sprite.png
NiukeWangMingqiBishiMianshiQiuzhiGonglveSidaXingye20202021/img/apple-touch-icon.png
NiukeWangMingqiBishiMianshiQiuzhiGonglveSidaXingye20202021/img/cancelfullscreen.png
NiukeWangMingqiBishiMianshiQiuzhiGonglveSidaXingye20202021/img/close.png
NiukeWangMingqiBishiMianshiQiuzhiGonglveSidaXingye20202021/img/fullscreen.png
NiukeWangMingqiBishiMianshiQiuzhiGonglveSidaXingye20202021/img/loader.gif
NiukeWangMingqiBishiMianshiQiuzhiGonglveSidaXingye20202021/img/menu-icon.png
NiukeWangMingqiBishiMianshiQiuzhiGonglveSidaXingye20202021/img/save.png
NiukeWangMingqiBishiMianshiQiuzhiGonglveSidaXingye20202021/img/saved.png
niuke_wang_mingqi_bishi_mianshi_qiuzhi_gonglve_sida_xingye_2020_2021-2024.3.5.0.dist-info/METADATA
niuke_wang_mingqi_bishi_mianshi_qiuzhi_gonglve_sida_xingye_2020_2021-2024.3.5.0.dist-info/WHEEL
niuke_wang_mingqi_bishi_mianshi_qiuzhi_gonglve_sida_xingye_2020_2021-2024.3.5.0.dist-info/entry_points.txt
niuke_wang_mingqi_bishi_mianshi_qiuzhi_gonglve_sida_xingye_2020_2021-2024.3.5.0.dist-info/top_level.txt
niuke_wang_mingqi_bishi_mianshi_qiuzhi_gonglve_sida_xingye_2020_2021-2024.3.5.0.dist-info/RECORD
